nested_fit.libs/libgomp-a34b3233.so.1.0.0
nested_fit.libs/libquadmath-96973f99.so.0.0.0
pynested_fit/__init__.py
pynested_fit/cliw.py
pynested_fit/evaluator.py
pynested_fit/metadata.py
pynested_fit/nested_fit5.5.4
pynested_fit/nested_res.py
pynested_fit/nested_run.py
pynested_fit/utils.py
pynested_fit/widgets/__init__.py
pynested_fit/widgets/bar.py
pynested_fit/widgets/errorui.py
pynested_fit/widgets/hfinder.py
pynested_fit/widgets/plot.py
pynested_fit/widgets/timer.py
pynested_fit/widgets/var.py
nested_fit-5.5.4.dist-info/LICENSE
nested_fit-5.5.4.dist-info/METADATA
nested_fit-5.5.4.dist-info/WHEEL
nested_fit-5.5.4.dist-info/entry_points.txt
nested_fit-5.5.4.dist-info/top_level.txt
nested_fit-5.5.4.dist-info/RECORD
