Metadata-Version: 2.1
Name: nested_fit
Version: 5.5.4
Summary: The nested_fit package.
Author: Martino Trassinelli, Lune Maillard, César Godinho
Project-URL: Homepage, https://github.com/martinit18/nested_fit
Project-URL: Bug Tracker, https://github.com/martinit18/nested_fit/issues
Classifier: Programming Language :: Fortran
Classifier: Programming Language :: C++
Classifier: Programming Language :: Python :: 3
Classifier: Operating System :: OS Independent
License-File: LICENSE
Requires-Dist: pandas
Requires-Dist: numpy
Requires-Dist: matplotlib
Requires-Dist: scipy
Requires-Dist: getdist
Requires-Dist: rich
Requires-Dist: plotly
Requires-Dist: psutil
Requires-Dist: anesthetic
Requires-Dist: plotext
